{"nodes": [{"id": "c_src_dnevnikflutter_lib_data_auth_service_dart", "label": "auth_service.dart", "file_type": "code", "source_file": "lib/data/auth_service.dart", "source_location": null}, {"id": "data_auth_service_authservice", "label": "AuthService", "file_type": "code", "source_file": "lib/data/auth_service.dart", "source_location": null}, {"id": "data_auth_service_projectid", "label": "_projectId", "file_type": "code", "source_file": "lib/data/auth_service.dart", "source_location": null}, {"id": "static_const_string", "label": "static const String", "file_type": "code", "source_file": null, "source_location": null}, {"id": "data_auth_service_databaseid", "label": "_databaseId", "file_type": "code", "source_file": "lib/data/auth_service.dart", "source_location": null}, {"id": "data_auth_service_firebasewebapikey", "label": "firebaseWebApiKey", "file_type": "code", "source_file": "lib/data/auth_service.dart", "source_location": null}, {"id": "static_string_get", "label": "static String get", "file_type": "code", "source_file": null, "source_location": null}, {"id": "data_auth_service_client", "label": "_client", "file_type": "code", "source_file": "lib/data/auth_service.dart", "source_location": null}, {"id": "client", "label": "Client", "file_type": "code", "source_file": null, "source_location": null}, {"id": "data_auth_service_timeout", "label": "_timeout", "file_type": "code", "source_file": "lib/data/auth_service.dart", "source_location": null}, {"id": "static_const_duration", "label": "static const Duration", "file_type": "code", "source_file": null, "source_location": null}, {"id": "data_auth_service_securestorage", "label": "_secureStorage", "file_type": "code", "source_file": "lib/data/auth_service.dart", "source_location": null}, {"id": "static_const", "label": "static const", "file_type": "code", "source_file": null, "source_location": null}, {"id": "data_auth_service_idtoken", "label": "_idToken", "file_type": "code", "source_file": "lib/data/auth_service.dart", "source_location": null}, {"id": "static_string", "label": "static String?", "file_type": "code", "source_file": null, "source_location": null}, {"id": "data_auth_service_base", "label": "_base", "file_type": "code", "source_file": "lib/data/auth_service.dart", "source_location": null}, {"id": "data_auth_service_generateclasscode", "label": "generateClassCode", "file_type": "code", "source_file": "lib/data/auth_service.dart", "source_location": null}, {"id": "data_auth_service_createclass", "label": "createClass", "file_type": "code", "source_file": "lib/data/auth_service.dart", "source_location": null}, {"id": "data_auth_service_joinclass", "label": "joinClass", "file_type": "code", "source_file": "lib/data/auth_service.dart", "source_location": null}, {"id": "data_auth_service_loginadmin", "label": "loginAdmin", "file_type": "code", "source_file": "lib/data/auth_service.dart", "source_location": null}, {"id": "data_auth_service_loadclassdata", "label": "loadClassData", "file_type": "code", "source_file": "lib/data/auth_service.dart", "source_location": null}, {"id": "data_auth_service_getclassinfo", "label": "getClassInfo", "file_type": "code", "source_file": "lib/data/auth_service.dart", "source_location": null}, {"id": "data_auth_service_updateclassschedule", "label": "updateClassSchedule", "file_type": "code", "source_file": "lib/data/auth_service.dart", "source_location": null}, {"id": "data_auth_service_deleteclass", "label": "deleteClass", "file_type": "code", "source_file": "lib/data/auth_service.dart", "source_location": null}, {"id": "data_auth_service_savesession", "label": "_saveSession", "file_type": "code", "source_file": "lib/data/auth_service.dart", "source_location": null}, {"id": "data_auth_service_getsavedclassid", "label": "getSavedClassId", "file_type": "code", "source_file": "lib/data/auth_service.dart", "source_location": null}, {"id": "data_auth_service_getsavedrole", "label": "getSavedRole", "file_type": "code", "source_file": "lib/data/auth_service.dart", "source_location": null}, {"id": "data_auth_service_logout", "label": "logout", "file_type": "code", "source_file": "lib/data/auth_service.dart", "source_location": null}, {"id": "data_auth_service_restoresession", "label": "restoreSession", "file_type": "code", "source_file": "lib/data/auth_service.dart", "source_location": null}, {"id": "data_auth_service_deletehomeworksubcollection", "label": "_deleteHomeworkSubcollection", "file_type": "code", "source_file": "lib/data/auth_service.dart", "source_location": null}, {"id": "data_auth_service_buildschedulemap", "label": "_buildScheduleMap", "file_type": "code", "source_file": "lib/data/auth_service.dart", "source_location": null}, {"id": "data_auth_service_buildclassdoc", "label": "_buildClassDoc", "file_type": "code", "source_file": "lib/data/auth_service.dart", "source_location": null}, {"id": "dart_convert", "label": "dart:convert", "file_type": "code", "source_file": null, "source_location": null}, {"id": "dart_math", "label": "dart:math", "file_type": "code", "source_file": null, "source_location": null}, {"id": "package_flutter_foundation_dart", "label": "package:flutter/foundation.dart", "file_type": "code", "source_file": null, "source_location": null}, {"id": "package_http_http_dart", "label": "package:http/http.dart", "file_type": "code", "source_file": null, "source_location": null}, {"id": "package_shared_preferences_shared_preferences_dart", "label": "package:shared_preferences/shared_preferences.dart", "file_type": "code", "source_file": null, "source_location": null}, {"id": "package_flutter_dotenv_flutter_dotenv_dart", "label": "package:flutter_dotenv/flutter_dotenv.dart", "file_type": "code", "source_file": null, "source_location": null}, {"id": "package_flutter_secure_storage_flutter_secure_storage_dart", "label": "package:flutter_secure_storage/flutter_secure_storage.dart", "file_type": "code", "source_file": null, "source_location": null}, {"id": "schedule_data_dart", "label": "schedule_data.dart", "file_type": "code", "source_file": null, "source_location": null}], "edges": [{"source": "c_src_dnevnikflutter_lib_data_auth_service_dart", "target": "data_auth_service_authservice", "relation": "defines", "confidence": "EXTRACTED", "confidence_score": 1.0, "source_file": "lib/data/auth_service.dart", "source_location": null, "weight": 1.0}, {"source": "c_src_dnevnikflutter_lib_data_auth_service_dart", "target": "data_auth_service_projectid", "relation": "defines", "confidence": "EXTRACTED", "confidence_score": 1.0, "source_file": "lib/data/auth_service.dart", "source_location": null, "weight": 1.0}, {"source": "c_src_dnevnikflutter_lib_data_auth_service_dart", "target": "static_const_string", "relation": "references", "confidence": "EXTRACTED", "confidence_score": 1.0, "source_file": "lib/data/auth_service.dart", "source_location": null, "weight": 1.0, "context": "variable_type"}, {"source": "c_src_dnevnikflutter_lib_data_auth_service_dart", "target": "data_auth_service_databaseid", "relation": "defines", "confidence": "EXTRACTED", "confidence_score": 1.0, "source_file": "lib/data/auth_service.dart", "source_location": null, "weight": 1.0}, {"source": "c_src_dnevnikflutter_lib_data_auth_service_dart", "target": "static_const_string", "relation": "references", "confidence": "EXTRACTED", "confidence_score": 1.0, "source_file": "lib/data/auth_service.dart", "source_location": null, "weight": 1.0, "context": "variable_type"}, {"source": "c_src_dnevnikflutter_lib_data_auth_service_dart", "target": "data_auth_service_firebasewebapikey", "relation": "defines", "confidence": "EXTRACTED", "confidence_score": 1.0, "source_file": "lib/data/auth_service.dart", "source_location": null, "weight": 1.0}, {"source": "c_src_dnevnikflutter_lib_data_auth_service_dart", "target": "static_string_get", "relation": "references", "confidence": "EXTRACTED", "confidence_score": 1.0, "source_file": "lib/data/auth_service.dart", "source_location": null, "weight": 1.0, "context": "variable_type"}, {"source": "c_src_dnevnikflutter_lib_data_auth_service_dart", "target": "data_auth_service_client", "relation": "defines", "confidence": "EXTRACTED", "confidence_score": 1.0, "source_file": "lib/data/auth_service.dart", "source_location": null, "weight": 1.0}, {"source": "c_src_dnevnikflutter_lib_data_auth_service_dart", "target": "client", "relation": "references", "confidence": "EXTRACTED", "confidence_score": 1.0, "source_file": "lib/data/auth_service.dart", "source_location": null, "weight": 1.0, "context": "variable_type"}, {"source": "c_src_dnevnikflutter_lib_data_auth_service_dart", "target": "data_auth_service_timeout", "relation": "defines", "confidence": "EXTRACTED", "confidence_score": 1.0, "source_file": "lib/data/auth_service.dart", "source_location": null, "weight": 1.0}, {"source": "c_src_dnevnikflutter_lib_data_auth_service_dart", "target": "static_const_duration", "relation": "references", "confidence": "EXTRACTED", "confidence_score": 1.0, "source_file": "lib/data/auth_service.dart", "source_location": null, "weight": 1.0, "context": "variable_type"}, {"source": "c_src_dnevnikflutter_lib_data_auth_service_dart", "target": "data_auth_service_securestorage", "relation": "defines", "confidence": "EXTRACTED", "confidence_score": 1.0, "source_file": "lib/data/auth_service.dart", "source_location": null, "weight": 1.0}, {"source": "c_src_dnevnikflutter_lib_data_auth_service_dart", "target": "static_const", "relation": "references", "confidence": "EXTRACTED", "confidence_score": 1.0, "source_file": "lib/data/auth_service.dart", "source_location": null, "weight": 1.0, "context": "variable_type"}, {"source": "c_src_dnevnikflutter_lib_data_auth_service_dart", "target": "data_auth_service_idtoken", "relation": "defines", "confidence": "EXTRACTED", "confidence_score": 1.0, "source_file": "lib/data/auth_service.dart", "source_location": null, "weight": 1.0}, {"source": "c_src_dnevnikflutter_lib_data_auth_service_dart", "target": "static_string", "relation": "references", "confidence": "EXTRACTED", "confidence_score": 1.0, "source_file": "lib/data/auth_service.dart", "source_location": null, "weight": 1.0, "context": "variable_type"}, {"source": "c_src_dnevnikflutter_lib_data_auth_service_dart", "target": "data_auth_service_idtoken", "relation": "defines", "confidence": "EXTRACTED", "confidence_score": 1.0, "source_file": "lib/data/auth_service.dart", "source_location": null, "weight": 1.0}, {"source": "c_src_dnevnikflutter_lib_data_auth_service_dart", "target": "static_string_get", "relation": "references", "confidence": "EXTRACTED", "confidence_score": 1.0, "source_file": "lib/data/auth_service.dart", "source_location": null, "weight": 1.0, "context": "variable_type"}, {"source": "c_src_dnevnikflutter_lib_data_auth_service_dart", "target": "data_auth_service_base", "relation": "defines", "confidence": "EXTRACTED", "confidence_score": 1.0, "source_file": "lib/data/auth_service.dart", "source_location": null, "weight": 1.0}, {"source": "c_src_dnevnikflutter_lib_data_auth_service_dart", "target": "static_string_get", "relation": "references", "confidence": "EXTRACTED", "confidence_score": 1.0, "source_file": "lib/data/auth_service.dart", "source_location": null, "weight": 1.0, "context": "variable_type"}, {"source": "c_src_dnevnikflutter_lib_data_auth_service_dart", "target": "data_auth_service_generateclasscode", "relation": "defines", "confidence": "EXTRACTED", "confidence_score": 1.0, "source_file": "lib/data/auth_service.dart", "source_location": null, "weight": 1.0}, {"source": "c_src_dnevnikflutter_lib_data_auth_service_dart", "target": "data_auth_service_createclass", "relation": "defines", "confidence": "EXTRACTED", "confidence_score": 1.0, "source_file": "lib/data/auth_service.dart", "source_location": null, "weight": 1.0}, {"source": "c_src_dnevnikflutter_lib_data_auth_service_dart", "target": "data_auth_service_joinclass", "relation": "defines", "confidence": "EXTRACTED", "confidence_score": 1.0, "source_file": "lib/data/auth_service.dart", "source_location": null, "weight": 1.0}, {"source": "c_src_dnevnikflutter_lib_data_auth_service_dart", "target": "data_auth_service_loginadmin", "relation": "defines", "confidence": "EXTRACTED", "confidence_score": 1.0, "source_file": "lib/data/auth_service.dart", "source_location": null, "weight": 1.0}, {"source": "c_src_dnevnikflutter_lib_data_auth_service_dart", "target": "data_auth_service_loadclassdata", "relation": "defines", "confidence": "EXTRACTED", "confidence_score": 1.0, "source_file": "lib/data/auth_service.dart", "source_location": null, "weight": 1.0}, {"source": "c_src_dnevnikflutter_lib_data_auth_service_dart", "target": "data_auth_service_getclassinfo", "relation": "defines", "confidence": "EXTRACTED", "confidence_score": 1.0, "source_file": "lib/data/auth_service.dart", "source_location": null, "weight": 1.0}, {"source": "c_src_dnevnikflutter_lib_data_auth_service_dart", "target": "data_auth_service_updateclassschedule", "relation": "defines", "confidence": "EXTRACTED", "confidence_score": 1.0, "source_file": "lib/data/auth_service.dart", "source_location": null, "weight": 1.0}, {"source": "c_src_dnevnikflutter_lib_data_auth_service_dart", "target": "data_auth_service_deleteclass", "relation": "defines", "confidence": "EXTRACTED", "confidence_score": 1.0, "source_file": "lib/data/auth_service.dart", "source_location": null, "weight": 1.0}, {"source": "c_src_dnevnikflutter_lib_data_auth_service_dart", "target": "data_auth_service_savesession", "relation": "defines", "confidence": "EXTRACTED", "confidence_score": 1.0, "source_file": "lib/data/auth_service.dart", "source_location": null, "weight": 1.0}, {"source": "c_src_dnevnikflutter_lib_data_auth_service_dart", "target": "data_auth_service_getsavedclassid", "relation": "defines", "confidence": "EXTRACTED", "confidence_score": 1.0, "source_file": "lib/data/auth_service.dart", "source_location": null, "weight": 1.0}, {"source": "c_src_dnevnikflutter_lib_data_auth_service_dart", "target": "data_auth_service_getsavedrole", "relation": "defines", "confidence": "EXTRACTED", "confidence_score": 1.0, "source_file": "lib/data/auth_service.dart", "source_location": null, "weight": 1.0}, {"source": "c_src_dnevnikflutter_lib_data_auth_service_dart", "target": "data_auth_service_logout", "relation": "defines", "confidence": "EXTRACTED", "confidence_score": 1.0, "source_file": "lib/data/auth_service.dart", "source_location": null, "weight": 1.0}, {"source": "c_src_dnevnikflutter_lib_data_auth_service_dart", "target": "data_auth_service_restoresession", "relation": "defines", "confidence": "EXTRACTED", "confidence_score": 1.0, "source_file": "lib/data/auth_service.dart", "source_location": null, "weight": 1.0}, {"source": "c_src_dnevnikflutter_lib_data_auth_service_dart", "target": "data_auth_service_deletehomeworksubcollection", "relation": "defines", "confidence": "EXTRACTED", "confidence_score": 1.0, "source_file": "lib/data/auth_service.dart", "source_location": null, "weight": 1.0}, {"source": "c_src_dnevnikflutter_lib_data_auth_service_dart", "target": "data_auth_service_buildschedulemap", "relation": "defines", "confidence": "EXTRACTED", "confidence_score": 1.0, "source_file": "lib/data/auth_service.dart", "source_location": null, "weight": 1.0}, {"source": "c_src_dnevnikflutter_lib_data_auth_service_dart", "target": "data_auth_service_buildclassdoc", "relation": "defines", "confidence": "EXTRACTED", "confidence_score": 1.0, "source_file": "lib/data/auth_service.dart", "source_location": null, "weight": 1.0}, {"source": "c_src_dnevnikflutter_lib_data_auth_service_dart", "target": "dart_convert", "relation": "imports", "confidence": "EXTRACTED", "confidence_score": 1.0, "source_file": "lib/data/auth_service.dart", "source_location": null, "weight": 1.0}, {"source": "c_src_dnevnikflutter_lib_data_auth_service_dart", "target": "dart_math", "relation": "imports", "confidence": "EXTRACTED", "confidence_score": 1.0, "source_file": "lib/data/auth_service.dart", "source_location": null, "weight": 1.0}, {"source": "c_src_dnevnikflutter_lib_data_auth_service_dart", "target": "package_flutter_foundation_dart", "relation": "imports", "confidence": "EXTRACTED", "confidence_score": 1.0, "source_file": "lib/data/auth_service.dart", "source_location": null, "weight": 1.0}, {"source": "c_src_dnevnikflutter_lib_data_auth_service_dart", "target": "package_http_http_dart", "relation": "imports", "confidence": "EXTRACTED", "confidence_score": 1.0, "source_file": "lib/data/auth_service.dart", "source_location": null, "weight": 1.0}, {"source": "c_src_dnevnikflutter_lib_data_auth_service_dart", "target": "package_shared_preferences_shared_preferences_dart", "relation": "imports", "confidence": "EXTRACTED", "confidence_score": 1.0, "source_file": "lib/data/auth_service.dart", "source_location": null, "weight": 1.0}, {"source": "c_src_dnevnikflutter_lib_data_auth_service_dart", "target": "package_flutter_dotenv_flutter_dotenv_dart", "relation": "imports", "confidence": "EXTRACTED", "confidence_score": 1.0, "source_file": "lib/data/auth_service.dart", "source_location": null, "weight": 1.0}, {"source": "c_src_dnevnikflutter_lib_data_auth_service_dart", "target": "package_flutter_secure_storage_flutter_secure_storage_dart", "relation": "imports", "confidence": "EXTRACTED", "confidence_score": 1.0, "source_file": "lib/data/auth_service.dart", "source_location": null, "weight": 1.0}, {"source": "c_src_dnevnikflutter_lib_data_auth_service_dart", "target": "schedule_data_dart", "relation": "imports", "confidence": "EXTRACTED", "confidence_score": 1.0, "source_file": "lib/data/auth_service.dart", "source_location": null, "weight": 1.0}]}