{"0": "Admin Panel UI", "1": "App Entrypoint & Setup", "2": "Class Schedule Schema", "3": "UI Custom Painting & Effects", "4": "Firestore Data Operations", "5": "AI Chat Widget & Logic", "6": "macOS Native Bridges", "7": "App Theme & Styles", "8": "Homework Creation UI", "9": "Windows Win32 Windowing", "10": "Class Creation UI", "11": "Image Files & System Paths", "12": "Diary & Calendar UI", "13": "Common Top Bars & Navigation", "14": "Main Navigation Shell", "15": "Image Rendering Widgets", "16": "User Auth Service", "17": "Linux GTK Platform Runner", "18": "Join Class UI", "19": "Authentication Router", "20": "Admin Tab Layouts", "21": "Services Integration Tests", "22": "Windows App Entrypoint", "23": "PWA Web Settings", "24": "Gemini AI Service Client", "25": "Windows Shell Engine", "26": "LLDB Debugger Utilities", "27": "Core Concepts & Config", "28": "Widget Behavior Tests", "29": "Android Plugin Registry", "30": "Windows Shell Declarations", "31": "Android App Entrypoint", "32": "iOS Plugin Registrant", "33": "iOS Build Config", "34": "macOS Build Config", "35": "Android Build Gradle", "36": "Android Gradle settings", "37": "Android App Gradle", "38": "iOS Plugin Registry Header", "39": "Linux Plugin Registry Header", "40": "Linux App Header", "41": "iOS Bridging Header", "42": "Windows Plugin Registry Header", "43": "Windows Win32 Window Header"}